version_builder-0.5.1.dist-info/METADATA
version_builder-0.5.1.dist-info/WHEEL
version_builder-0.5.1.dist-info/entry_points.txt
version_builder/__init__.py
version_builder/cli.py
version_builder/constants.py
version_builder/exceptions.py
version_builder/files.py
version_builder/git.py
version_builder/logger.py
version_builder/version.py
version_builder-0.5.1.dist-info/RECORD
