Metadata-Version: 2.1
Name: version_builder
Version: 0.5.1
Summary: yet another version bumper
Author-Email: dkurchigin <kurchigin.dmitry@yandex.ru>
License: MIT
Classifier: Programming Language :: Python :: 3
Classifier: Programming Language :: Python
Classifier: Environment :: Console
Classifier: Typing :: Typed
Classifier: Programming Language :: Python :: 3 :: Only
Classifier: Programming Language :: Python :: 3.10
Classifier: Programming Language :: Python :: 3.11
Classifier: Programming Language :: Python :: 3.12
Classifier: Programming Language :: Python :: 3.13
Project-URL: Homepage, https://gitverse.ru/dkurchigin/version_builder
Project-URL: Source, https://gitverse.ru/dkurchigin/version_builder
Requires-Python: >=3.10
Requires-Dist: GitPython>=3.1.45
Requires-Dist: semver>=3.0.4
Requires-Dist: pathlib>=1.0.1
